{
	"skins": {
		"airship": {
			"ally": [
				{
					"description": "",
					"images": {},
					"name": "飛空艇"
				}
			],
			"enemy": [
				{
					"description": "",
					"images": {},
					"name": "ワイバーン"
				}
			]
		},
		"archer": {
			"ally": [
				{
					"description": "",
					"images": {},
					"name": "アーチャー"
				}
			],
			"enemy": [
				{
					"description": "",
					"images": {},
					"name": "リザードマン"
				}
			]
		},
		"ballista": {
			"ally": [
				{
					"description": "",
					"images": {},
					"name": "バリスタ"
				}
			],
			"enemy": [
				{
					"description": "",
					"images": {},
					"name": "マンドラゴラ"
				}
			]
		},
		"birdman": {
			"ally": [
				{
					"description": "",
					"images": {},
					"name": "バードマン"
				}
			],
			"enemy": [
				{
					"description": "",
					"images": {},
					"name": "ハーピー"
				}
			]
		},
		"bishop": {
			"ally": [
				{
					"description": "",
					"images": {},
					"name": "ビショップ"
				}
			],
			"enemy": [
				{
					"description": "",
					"images": {},
					"name": "ノーム"
				}
			]
		},
		"cleric": {
			"ally": [
				{
					"description": "",
					"images": {},
					"name": "クレリック"
				}
			],
			"enemy": [
				{
					"description": "",
					"images": {},
					"name": "ゴブリン"
				}
			]
		},
		"dragon": {
			"ally": [],
			"enemy": [
				{
					"description": "",
					"images": {},
					"name": "ドラゴン"
				}
			]
		},
		"dragon_knight": {
			"ally": [
				{
					"description": "",
					"images": {},
					"name": "ドラゴンナイト"
				}
			],
			"enemy": [
				{
					"description": "",
					"images": {},
					"name": "グリフォン"
				}
			]
		},
		"dwarf": {
			"ally": [
				{
					"description": "",
					"images": {},
					"name": "ドワーフ"
				}
			],
			"enemy": [
				{
					"description": "",
					"images": {},
					"name": "トロール"
				}
			]
		},
		"elf": {
			"ally": [
				{
					"description": "",
					"images": {},
					"name": "エルフ"
				}
			],
			"enemy": [
				{
					"description": "",
					"images": {},
					"name": "ダークエルフ"
				}
			]
		},
		"fighter": {
			"ally": [
				{
					"description": "",
					"images": {},
					"name": "ファイター"
				}
			],
			"enemy": [
				{
					"description": "",
					"images": {},
					"name": "オーク"
				}
			]
		},
		"halfling": {
			"ally": [
				{
					"description": "",
					"images": {},
					"name": "ハーフリング"
				}
			],
			"enemy": [
				{
					"description": "",
					"images": {},
					"name": "アラクネ"
				}
			]
		},
		"hunter": {
			"ally": [
				{
					"description": "",
					"images": {},
					"name": "ハンター"
				}
			],
			"enemy": [
				{
					"description": "",
					"images": {},
					"name": "ケンタウロス"
				}
			]
		},
		"knight": {
			"ally": [
				{
					"description": "",
					"images": {},
					"name": "ナイト"
				}
			],
			"enemy": [
				{
					"description": "",
					"images": {},
					"name": "ミノタウロス"
				}
			]
		},
		"mercenary": {
			"ally": [
				{
					"description": "",
					"images": {},
					"name": "マーシナリー"
				}
			],
			"enemy": [
				{
					"description": "",
					"images": {},
					"name": "バーサーカー"
				}
			]
		},
		"monk": {
			"ally": [
				{
					"description": "",
					"images": {},
					"name": "モンク"
				}
			],
			"enemy": [
				{
					"description": "",
					"images": {},
					"name": "コボルト"
				}
			]
		},
		"ninja": {
			"ally": [
				{
					"description": "",
					"images": {},
					"name": "ニンジャ"
				}
			],
			"enemy": [
				{
					"description": "",
					"images": {},
					"name": "ワーウルフ"
				}
			]
		},
		"novice": {
			"ally": [
				{
					"description": "",
					"images": {},
					"name": "ノービス"
				}
			],
			"enemy": [
				{
					"description": "",
					"images": {},
					"name": "スケルトン"
				}
			]
		},
		"paladin": {
			"ally": [
				{
					"description": "",
					"images": {},
					"name": "パラディン"
				}
			],
			"enemy": [
				{
					"description": "",
					"images": {},
					"name": "ゴブリンロード"
				}
			]
		},
		"priest": {
			"ally": [
				{
					"description": "",
					"images": {},
					"name": "プリースト"
				}
			],
			"enemy": [
				{
					"description": "",
					"images": {},
					"name": "ホブゴブリン"
				}
			]
		},
		"samurai": {
			"ally": [
				{
					"description": "",
					"images": {},
					"name": "サムライ"
				}
			],
			"enemy": [
				{
					"description": "",
					"images": {},
					"name": "オーガ"
				}
			]
		},
		"sniper": {
			"ally": [
				{
					"description": "",
					"images": {},
					"name": "スナイパー"
				}
			],
			"enemy": [
				{
					"description": "",
					"images": {},
					"name": "メデューサ"
				}
			]
		},
		"sorcerer": {
			"ally": [
				{
					"description": "",
					"images": {},
					"name": "ソーサラー"
				}
			],
			"enemy": [
				{
					"description": "",
					"images": {},
					"name": "ゴーレム"
				}
			]
		},
		"thief": {
			"ally": [
				{
					"description": "",
					"images": {},
					"name": "シーフ"
				}
			],
			"enemy": [
				{
					"description": "",
					"images": {},
					"name": "ヴァンパイア"
				}
			]
		},
		"wagon": {
			"ally": [
				{
					"description": "",
					"images": {},
					"name": "馬車"
				}
			],
			"enemy": [
				{
					"description": "",
					"images": {},
					"name": "モンスターチャリオッツ"
				}
			]
		},
		"witch": {
			"ally": [
				{
					"description": "",
					"images": {},
					"name": "ウィッチ"
				}
			],
			"enemy": [
				{
					"description": "",
					"images": {},
					"name": "シャーマン"
				}
			]
		},
		"wizard": {
			"ally": [
				{
					"description": "",
					"images": {},
					"name": "ウィザード"
				}
			],
			"enemy": [
				{
					"description": "",
					"images": {},
					"name": "ネクロマンサー"
				}
			]
		}
	}
}
